damo-server
damo.cpython-39-darwin.so
damo_embedding/config.py
damo_embedding/util.py
damo_embedding/graph.py
damo_embedding/__init__.py
damo_embedding/inference.py
damo_embedding/trainning.py
damo_embedding/.dylibs/librocksdb.8.10.0.dylib
damo_embedding/.dylibs/liblz4.1.9.4.dylib
damo_embedding/.dylibs/libgflags.2.2.2.dylib
damo_embedding/.dylibs/libsnappy.1.1.10.dylib
damo_embedding/.dylibs/libzstd.1.5.5.dylib
damo_embedding-1.1.12.dist-info/RECORD
damo_embedding-1.1.12.dist-info/LICENSE
damo_embedding-1.1.12.dist-info/WHEEL
damo_embedding-1.1.12.dist-info/top_level.txt
damo_embedding-1.1.12.dist-info/METADATA
