Metadata-Version: 2.1
Name: damo-embedding
Version: 1.1.12
Summary: Python wrapper for damo, a set of fast and robust hash functions.
Home-page: https://github.com/uopensail/damo-embedding
Author: timepi
Author-email: 
License: License :: AGLP3
Keywords: sparse embedding using rocksdb,parameter server,ftrl,adam,adamw,adagrad
Classifier: Development Status :: 5 - Production/Stable
Classifier: Intended Audience :: Developers
Classifier: Programming Language :: Python :: 3
Classifier: Programming Language :: Python :: 3.6
Classifier: Programming Language :: Python :: 3.7
Classifier: Programming Language :: Python :: 3.8
Classifier: Programming Language :: Python :: 3.9
Classifier: Topic :: Software Development :: Libraries
Classifier: Topic :: Utilities
Requires-Python: >=3.6
License-File: LICENSE
Requires-Dist: numpy >=1.19.0
Requires-Dist: requests >=2.22.0
